legume/__init__.py
legume/backend.py
legume/constants.py
legume/gds.py
legume/minimize.py
legume/primitives.py
legume/print_backend.py
legume/print_utils.py
legume/utils.py
legume/viz.py
legume/exc/__init__.py
legume/exc/exc.py
legume/gme/__init__.py
legume/gme/gme.py
legume/gme/matrix_elements.py
legume/gme/slab_modes.py
legume/phc/__init__.py
legume/phc/lattice.py
legume/phc/layer.py
legume/phc/phc.py
legume/phc/shapes.py
legume/pol/__init__.py
legume/pol/pol.py
legume/pwe/__init__.py
legume/pwe/pwe.py
legume_gme-1.0.2.dist-info/LICENSE
legume_gme-1.0.2.dist-info/METADATA
legume_gme-1.0.2.dist-info/WHEEL
legume_gme-1.0.2.dist-info/top_level.txt
legume_gme-1.0.2.dist-info/RECORD
