Metadata-Version: 2.1
Name: legume-gme
Version: 1.0.2
Summary: Differentiable plane-wave and guided-mode expansion for photonic crystals
Home-page: https://github.com/fancompute/legume
Author: Momchil Minkov
Author-email: momchilmm@gmail.com
Classifier: Programming Language :: Python :: 3
Classifier: License :: OSI Approved :: MIT License
Classifier: Operating System :: OS Independent
License-File: LICENSE
Requires-Dist: matplotlib >=3.0.3
Requires-Dist: numpy <2.0.0,>=1.16.2
Requires-Dist: scipy >=1.2.1
